RE20005uno/__init__.py
RE20005uno/bisection.py
RE20005uno/cramer.py
RE20005uno/gauss.py
RE20005uno/gauss_jordan.py
RE20005uno/gauss_seidel.py
RE20005uno/jacobi.py
RE20005uno/lu.py
re20005uno-0.1.0.dist-info/licenses/LICENSE
re20005uno-0.1.0.dist-info/METADATA
re20005uno-0.1.0.dist-info/WHEEL
re20005uno-0.1.0.dist-info/top_level.txt
re20005uno-0.1.0.dist-info/RECORD
