Metadata-Version: 2.4
Name: re20005uno
Version: 0.1.0
Summary: Librería de métodos numéricos para sistemas de ecuaciones
Home-page: https://github.com/re20005/re20005uno
Author: Gerson
Classifier: Programming Language :: Python :: 3
Classifier: License :: OSI Approved :: MIT License
Classifier: Operating System :: OS Independent
Requires-Python: >=3.6
License-File: LICENSE
Requires-Dist: numpy
Dynamic: author
Dynamic: classifier
Dynamic: description
Dynamic: description-content-type
Dynamic: home-page
Dynamic: license-file
Dynamic: requires-dist
Dynamic: requires-python
Dynamic: summary
